pyPPG/__init__.py
pyPPG/biomarkers.py
pyPPG/datahandling.py
pyPPG/example.py
pyPPG/fiducials.py
pyPPG/ppg_sqi.py
pyPPG/preproc.py
pyPPG/pack_ppg/_ErrorHandler.py
pyPPG/pack_ppg/__init__.py
pyPPG/ppg_bm/__init__.py
pyPPG/ppg_bm/bm_extraction.py
pyPPG/ppg_bm/derivs_ratios.py
pyPPG/ppg_bm/ppg_derivs.py
pyPPG/ppg_bm/ppg_sig.py
pyPPG/ppg_bm/sig_ratios.py
pyPPG/ppg_bm/statistics.py
pyPPG/validation/__init__.py
pyPPG/validation/pw_anal.py
pyPPG/validation/run_validation.py
pyPPG-1.0.73.dist-info/AUTHORS.rst
pyPPG-1.0.73.dist-info/LICENSE.txt
pyPPG-1.0.73.dist-info/METADATA
pyPPG-1.0.73.dist-info/WHEEL
pyPPG-1.0.73.dist-info/top_level.txt
pyPPG-1.0.73.dist-info/RECORD
