Metadata-Version: 2.1
Name: pyPPG
Version: 1.0.73
Summary: pyPPG: a python toolbox for PPG morphological analysis.
Home-page: https://github.com/godamartonaron/GODA_pyPPG
Author: Marton A. Goda, PhD; Peter H. Charlton, PhD
Author-email: marton.goda@campus.technion.ac.il
Project-URL: Bug Tracker, https://github.com/pypa/sampleproject/issues
Classifier: Programming Language :: Python :: 3
Classifier: License :: OSI Approved :: GNU Affero General Public License v3
Classifier: Operating System :: OS Independent
Requires-Python: >=3.10
License-File: LICENSE.txt
License-File: AUTHORS.rst
Requires-Dist: scipy (==1.9.1)
Requires-Dist: numpy (==1.23.2)
Requires-Dist: dotmap (==1.3.30)
Requires-Dist: pandas (==1.4.4)
Requires-Dist: wfdb (==3.4.0)
Requires-Dist: mne (==1.5.0)
Requires-Dist: Eel (==0.14.0)
Requires-Dist: Jinja2 (==3.1.2)
Requires-Dist: MarkupSafe (==2.1.1)
Requires-Dist: Pillow (==9.2.0)
Requires-Dist: altgraph (==0.17.3)
Requires-Dist: appdirs (==1.4.4)
Requires-Dist: attrs (==22.1.0)
Requires-Dist: auto-py-to-exe (==2.23.1)
Requires-Dist: boltons (==21.0.0)
Requires-Dist: bottle (==0.12.23)
Requires-Dist: bottle-websocket (==0.2.9)
Requires-Dist: certifi (==2022.9.24)
Requires-Dist: cffi (==1.15.1)
Requires-Dist: chardet (==5.0.0)
Requires-Dist: charset-normalizer (==2.1.1)
Requires-Dist: colorama (==0.4.5)
Requires-Dist: contourpy (==1.0.5)
Requires-Dist: cycler (==0.11.0)
Requires-Dist: decorator (==5.1.1)
Requires-Dist: dotteddict (==2016.3.11)
Requires-Dist: face (==20.1.1)
Requires-Dist: fonttools (==4.37.1)
Requires-Dist: future (==0.18.2)
Requires-Dist: gevent (==21.12.0)
Requires-Dist: gevent-websocket (==0.10.1)
Requires-Dist: glom (==22.1.0)
Requires-Dist: greenlet (==1.1.3)
Requires-Dist: heartpy (==1.2.7)
Requires-Dist: idna (==3.4)
Requires-Dist: joblib (==1.2.0)
Requires-Dist: kiwisolver (==1.4.4)
Requires-Dist: matplotlib (==3.6.1)
Requires-Dist: mpldatacursor (==0.7.1)
Requires-Dist: packaging (==21.3)
Requires-Dist: parallel-map (==0.2.1)
Requires-Dist: patsy (==0.5.3)
Requires-Dist: pefile (==2022.5.30)
Requires-Dist: pip (==21.3.1)
Requires-Dist: pooch (==1.6.0)
Requires-Dist: pycparser (==2.21)
Requires-Dist: pyinstaller (==5.5)
Requires-Dist: pyinstaller-hooks-contrib (==2022.10)
Requires-Dist: pyparsing (==3.0.9)
Requires-Dist: python-dateutil (==2.8.2)
Requires-Dist: pytz (==2022.4)
Requires-Dist: pywin32-ctypes (==0.2.0)
Requires-Dist: requests (==2.28.1)
Requires-Dist: scikit-learn (==1.1.3)
Requires-Dist: setuptools (==60.2.0)
Requires-Dist: six (==1.16.0)
Requires-Dist: sphinx-rtd-theme (==1.3.0)
Requires-Dist: soundfile (==0.11.0)
Requires-Dist: statsmodels (==0.13.2)
Requires-Dist: threadpoolctl (==3.1.0)
Requires-Dist: tqdm (==4.64.1)
Requires-Dist: urllib3 (==1.26.12)
Requires-Dist: wheel (==0.37.1)
Requires-Dist: whichcraft (==0.6.1)
Requires-Dist: zope.event (==4.5.0)
Requires-Dist: zope.interface (==5.4.0)
